bmkg/__init__.py
bmkg/base.py
bmkg/client.py
bmkg/constants.py
bmkg/earthquake.py
bmkg/enums.py
bmkg/errors.py
bmkg/forecast.py
bmkg-1.0.4.dist-info/LICENSE
bmkg-1.0.4.dist-info/METADATA
bmkg-1.0.4.dist-info/WHEEL
bmkg-1.0.4.dist-info/top_level.txt
bmkg-1.0.4.dist-info/RECORD
