Metadata-Version: 2.1
Name: bmkg
Version: 1.0.4
Summary: Unofficial Python wrapper for the BMKG (Meteorology, Climatology, and Geophysical Agency) API.
Author: null8626
License: MIT
Project-URL: repository, https://github.com/null8626/bmkg
Project-URL: download_url, https://github.com/null8626/bmkg/archive/1.0.4.tar.gz
Keywords: weather,forecast,indonesia,weather-api,weather-forecast,bmkg
Classifier: Development Status :: 5 - Production/Stable
Classifier: Framework :: aiohttp
Classifier: Framework :: AsyncIO
Classifier: Intended Audience :: Education
Classifier: Intended Audience :: Developers
Classifier: Intended Audience :: Information Technology
Classifier: Topic :: Education
Classifier: Topic :: Internet
Classifier: Topic :: Scientific/Engineering
Classifier: Topic :: Scientific/Engineering :: Astronomy
Classifier: Topic :: Software Development
Classifier: Topic :: Software Development :: Libraries
Classifier: License :: OSI Approved :: MIT License
Classifier: Programming Language :: Python
Classifier: Programming Language :: Python :: 3
Classifier: Programming Language :: Python :: 3 :: Only
Classifier: Programming Language :: Python :: 3.7
Classifier: Programming Language :: Python :: 3.8
Classifier: Programming Language :: Python :: 3.9
Classifier: Programming Language :: Python :: 3.10
Classifier: Programming Language :: Python :: 3.11
Classifier: Programming Language :: Python :: 3.12
Requires-Python: >=3.7
License-File: LICENSE
Requires-Dist: aiohttp (>=3.0.0)
